stegvault/__init__.py
stegvault/cli.py
stegvault/app/__init__.py
stegvault/app/controllers/__init__.py
stegvault/app/controllers/crypto_controller.py
stegvault/app/controllers/vault_controller.py
stegvault/batch/__init__.py
stegvault/batch/core.py
stegvault/config/__init__.py
stegvault/config/core.py
stegvault/crypto/__init__.py
stegvault/crypto/core.py
stegvault/gallery/__init__.py
stegvault/gallery/core.py
stegvault/gallery/db.py
stegvault/gallery/operations.py
stegvault/gallery/search.py
stegvault/stego/__init__.py
stegvault/stego/dispatcher.py
stegvault/stego/jpeg_dct.py
stegvault/stego/png_lsb.py
stegvault/tui/__init__.py
stegvault/tui/app.py
stegvault/tui/screens.py
stegvault/tui/widgets.py
stegvault/utils/__init__.py
stegvault/utils/favorite_folders.py
stegvault/utils/image_format.py
stegvault/utils/json_output.py
stegvault/utils/passphrase.py
stegvault/utils/payload.py
stegvault/utils/updater.py
stegvault/vault/__init__.py
stegvault/vault/core.py
stegvault/vault/generator.py
stegvault/vault/operations.py
stegvault/vault/totp.py
stegvault-0.7.10.dist-info/licenses/LICENSE
stegvault-0.7.10.dist-info/METADATA
stegvault-0.7.10.dist-info/WHEEL
stegvault-0.7.10.dist-info/entry_points.txt
stegvault-0.7.10.dist-info/top_level.txt
stegvault-0.7.10.dist-info/RECORD
