Metadata-Version: 2.4
Name: stegvault
Version: 0.7.10
Summary: Password manager using steganography to embed encrypted credentials in images
Author: StegVault Contributors
License: MIT
Project-URL: Homepage, https://github.com/kalashnikxvxiii/stegvault
Project-URL: Repository, https://github.com/kalashnikxvxiii/stegvault
Project-URL: Issues, https://github.com/kalashnikxvxiii/stegvault/issues
Project-URL: Changelog, https://github.com/kalashnikxvxiii/stegvault/blob/main/CHANGELOG.md
Keywords: steganography,password-manager,encryption,cryptography,security,LSB,XChaCha20-Poly1305,Argon2id
Classifier: Development Status :: 3 - Alpha
Classifier: Intended Audience :: Developers
Classifier: Intended Audience :: End Users/Desktop
Classifier: Topic :: Security :: Cryptography
Classifier: Topic :: Security
Classifier: License :: OSI Approved :: MIT License
Classifier: Operating System :: OS Independent
Classifier: Programming Language :: Python :: 3
Classifier: Programming Language :: Python :: 3.9
Classifier: Programming Language :: Python :: 3.10
Classifier: Programming Language :: Python :: 3.11
Classifier: Programming Language :: Python :: 3.12
Classifier: Programming Language :: Python :: 3.13
Classifier: Programming Language :: Python :: 3.14
Requires-Python: >=3.9
License-File: LICENSE
Requires-Dist: PyNaCl>=1.5.0
Requires-Dist: argon2-cffi>=23.1.0
Requires-Dist: Pillow>=10.0.0
Requires-Dist: click>=8.1.0
Requires-Dist: numpy>=1.24.0
Requires-Dist: tomli>=2.0.0; python_version < "3.11"
Requires-Dist: tomli-w>=1.0.0
Requires-Dist: pyperclip>=1.8.0
Requires-Dist: pyotp>=2.9.0
Requires-Dist: qrcode>=7.4.0
Requires-Dist: zxcvbn>=4.4.28
Requires-Dist: jpeglib>=1.0.0
Requires-Dist: textual>=0.47.0
Provides-Extra: dev
Requires-Dist: pytest>=7.4.0; extra == "dev"
Requires-Dist: pytest-cov>=4.1.0; extra == "dev"
Requires-Dist: pytest-rerunfailures>=12.0; extra == "dev"
Requires-Dist: pytest-asyncio>=0.21.0; extra == "dev"
Requires-Dist: pytest-timeout>=2.1.0; extra == "dev"
Requires-Dist: black>=23.0.0; extra == "dev"
Requires-Dist: mypy>=1.5.0; extra == "dev"
Dynamic: license-file
